py_notes/__init__.py
py_notes/notes.py
py_notes/utils/__init__.py
py_notes/utils/databases/general.sqlite3
py_notes/utils/db.py
py_notes-1.0.4.dist-info/entry_points.txt
py_notes-1.0.4.dist-info/LICENSE
py_notes-1.0.4.dist-info/WHEEL
py_notes-1.0.4.dist-info/METADATA
py_notes-1.0.4.dist-info/RECORD
