Metadata-Version: 2.1
Name: py-notes
Version: 1.0.4
Summary: Take notes directly in your terminal.
Home-page: https://github.com/Saakshaat/notes-cli
License: MIT
Keywords: CLI,Notes,Poetry
Author: Saakshaat
Author-email: saakshaat2001@gmail.com
Requires-Python: >=3.6,<4.0
Classifier: License :: OSI Approved :: MIT License
Classifier: Programming Language :: Python :: 3
Classifier: Programming Language :: Python :: 3.6
Classifier: Programming Language :: Python :: 3.7
Classifier: Programming Language :: Python :: 3.8
Classifier: Programming Language :: Python :: 3.9
Requires-Dist: click (>=7.1.2,<8.0.0)
Project-URL: Repository, https://github.com/Saakshaat/notes-cli
